Products.PloneLanguageTool-3.2.10-py2.7-nspkg.pth
Products/PloneLanguageTool/LanguageTool.py
Products/PloneLanguageTool/__init__.py
Products/PloneLanguageTool/configure.zcml
Products/PloneLanguageTool/exportimport.py
Products/PloneLanguageTool/interfaces.py
Products/PloneLanguageTool/profiles.zcml
Products/PloneLanguageTool/tool.gif
Products/PloneLanguageTool/version.txt
Products/PloneLanguageTool/profiles/default/export_steps.xml
Products/PloneLanguageTool/profiles/default/import_steps.xml
Products/PloneLanguageTool/profiles/default/metadata.xml
Products/PloneLanguageTool/profiles/default/portal_languages.xml
Products/PloneLanguageTool/profiles/default/skins.xml
Products/PloneLanguageTool/profiles/default/toolset.xml
Products/PloneLanguageTool/skins/LanguageTool/isTranslatable.py
Products/PloneLanguageTool/skins/LanguageTool/switchLanguage.py
Products/PloneLanguageTool/tests/__init__.py
Products/PloneLanguageTool/tests/base.py
Products/PloneLanguageTool/tests/test_languagetool.py
Products/PloneLanguageTool/tests/test_negotiation.py
Products/PloneLanguageTool/www/config.zpt
Products.PloneLanguageTool-3.2.10.dist-info/METADATA
Products.PloneLanguageTool-3.2.10.dist-info/WHEEL
Products.PloneLanguageTool-3.2.10.dist-info/namespace_packages.txt
Products.PloneLanguageTool-3.2.10.dist-info/top_level.txt
Products.PloneLanguageTool-3.2.10.dist-info/RECORD
