Metadata-Version: 2.1
Name: Products.PloneLanguageTool
Version: 3.2.10
Summary: PloneLanguageTool allows you to set the available languages in your Plone site, select various fallback mechanisms, and control the use of flags for language selection and translations.
Home-page: https://pypi.org/project/Products.PloneLanguageTool
Author: Hanno Schlichting
Author-email: plone-developers@lists.sourceforge.net
License: GPL
Keywords: Zope CMF Plone i18n l10n flags
Platform: UNKNOWN
Classifier: Development Status :: 6 - Mature
Classifier: Framework :: Plone
Classifier: Framework :: Plone :: 4.3
Classifier: Framework :: Plone :: 5.0
Classifier: Framework :: Plone :: 5.1
Classifier: Framework :: Plone :: 5.2
Classifier: Framework :: Zope2
Classifier: License :: OSI Approved :: GNU General Public License (GPL)
Classifier: Programming Language :: Python
Classifier: Programming Language :: Python :: 2.6
Classifier: Programming Language :: Python :: 2.7
Requires-Dist: setuptools
Provides-Extra: test
Requires-Dist: Products.CMFTestCase ; extra == 'test'
